{"Jet25_bjdphi": 46, "Jet25_px": 45, "Jet25_dilepptratio": 19, "Jet25_bDiscriminator": 1, "Jet25_lepdrmin": 1, "Jet25_lepdphimax": 34, "Jet25_lepptratiomax": 1, "Jet25_chargedMultiplicity": 27, "Jet25_lepdetamin": 6, "Jet25_dilepmetptratio": 17, "Jet25_nonjdilepdeta": 33, "Jet25_pt": 1, "Jet25_eta": 32, "Jet25_pz": 41, "Jet25_chargedHadronEnergyFraction": 24, "Jet25_mult": 10, "Jet25_py": 38, "Jet25_nonjdilepdphi": 30, "Jet25_pfCombinedInclusiveSecondaryVertexV2BJetTags": 21, "Jet25_pfDeepCSVCvsLJetTags": 26, "Jet25_energy": 1, "Jet25_matchId": 1, "Jet25_electronEnergy": 29, "Jet25_lepptratiomin": 1, "Jet25_pfDeepCSVCvsBJetTags": 1, "Jet25_lepdphimin": 22, "Jet25_pfCombinedCvsLJetTags": 42, "Jet25_nonjdr": 3, "Jet25_dilepdeta": 43, "Jet25_photonEnergy": 16, "Jet25_lepdrmax": 1, "Jet25_bjdr": 5, "Jet25_qg": 4, "Jet25_nonjdeta": 39, "Jet25_nonjdilepdr": 13, "Jet25_ptD": 12, "Jet25_dilepdphi": 36, "Jet25_bjdeta": 20, "Jet25_nonjdilepptratio": 2, "Jet25_dilepdr": 15, "Jet25_pfJetProbabilityBJetTags": 25, "Jet25_bjptratio": 18, "Jet25_neutralHadEnergyFraction": 28, "Jet25_pfCombinedMVAV2BJetTags": 7, "Jet25_metptratio": 8, "Jet25_mass": 1, "Jet25_muonEnergyFraction": 37, "Jet25_chargedEmEnergyFraction": 40, "Jet25_phi": 44, "Jet25_nonjptratio": 14, "Jet25_numberOfConstituents": 23, "Jet25_pfCombinedCvsBJetTags": 11, "Jet25_nonjdphi": 31, "Jet25_lepdetamax": 9, "Jet25_axis2": 35}